Metadata-Version: 2.4
Name: llama-index-readers-milvus
Version: 0.4.1
Summary: llama-index readers milvus integration
Author-email: Your Name <you@example.com>
Maintainer: filip-halt
License-Expression: MIT
License-File: LICENSE
Requires-Python: <4.0,>=3.9
Requires-Dist: llama-index-core<0.15,>=0.13.0
Requires-Dist: pymilvus<3,>=2.3.6
